boto3_pydantic_geo_places/__init__.py
boto3_pydantic_geo_places/base_validator_model.py
boto3_pydantic_geo_places/geo_places_classes.py
boto3_pydantic_geo_places/geo_places_constants.py
boto3_pydantic_geo_places-1.0.2.dist-info/METADATA
boto3_pydantic_geo_places-1.0.2.dist-info/WHEEL
boto3_pydantic_geo_places-1.0.2.dist-info/RECORD
