Metadata-Version: 2.3
Name: boto3-pydantic-geo_places
Version: 1.0.2
Summary: Pydantic models for AWS Geo_places
Keywords: aws,boto3,pydantic,models,geo_places
Author: Alexy Grabov
Author-email: alexy.grabov@gmail.com
Requires-Python: >=3.9,<4.0
Classifier: Development Status :: 6 - Mature
Classifier: Intended Audience :: Developers
Classifier: License :: OSI Approved :: Apache Software License
Classifier: Programming Language :: Python :: 3
Classifier: Programming Language :: Python :: 3.9
Classifier: Programming Language :: Python :: 3.10
Classifier: Programming Language :: Python :: 3.11
Classifier: Programming Language :: Python :: 3.12
Classifier: Programming Language :: Python :: 3.13
Classifier: Topic :: Software Development :: Libraries :: Python Modules
Requires-Dist: botocore
Requires-Dist: pydantic (>=2.8.2,<3.0.0)
Project-URL: Homepage, https://coreoxide.github.io/aws_resource_validator/
Project-URL: Repository, https://github.com/CoreOxide/aws_resource_validator
